LICENSE.txt
MANIFEST.in
README.md
requirements.txt
setup.py
imagedatasetanalyzer/__init__.py
imagedatasetanalyzer.egg-info/PKG-INFO
imagedatasetanalyzer.egg-info/SOURCES.txt
imagedatasetanalyzer.egg-info/dependency_links.txt
imagedatasetanalyzer.egg-info/requires.txt
imagedatasetanalyzer.egg-info/top_level.txt
imagedatasetanalyzer/datasets/__init__.py
imagedatasetanalyzer/datasets/imagedataset.py
imagedatasetanalyzer/datasets/imagelabeldataset.py
imagedatasetanalyzer/embeddings/__init__.py
imagedatasetanalyzer/embeddings/embedding.py
imagedatasetanalyzer/embeddings/huggingfaceembedding.py
imagedatasetanalyzer/embeddings/medimageinsightembedding.py
imagedatasetanalyzer/embeddings/opencvlbpembedding.py
imagedatasetanalyzer/embeddings/tensorflowembedding.py
imagedatasetanalyzer/embeddings/torchembedding.py
imagedatasetanalyzer/models/__init__.py
imagedatasetanalyzer/models/agglomerativeclustering.py
imagedatasetanalyzer/models/clusteringbase.py
imagedatasetanalyzer/models/dbscanclustering.py
imagedatasetanalyzer/models/kmeansclustering.py
imagedatasetanalyzer/models/opticsclustering.py
imagedatasetanalyzer/utils/__init__.py
imagedatasetanalyzer/utils/metrics.py
imagedatasetanalyzer/utils/preprocessing.py
tests/test_analyze.py
tests/test_analyze_copy.py
tests/test_convert_multicolor.py
tests/test_embedding.py
tests/test_images.py
tests/test_medimageinsight.py
tests/test_names.py
tests/test_reduce.py
tests/test_reduction_process.py
tests/test_reduction_strategies.py