Metadata-Version: 2.4
Name: imagedatasetanalyzer
Version: 0.4.1
Summary: Image dataset analyzer using image embedding models and clustering methods.
Home-page: https://github.com/joortif/ImageDatasetAnalyzer
Author: Joaquin Ortiz de Murua Ferrero
Author-email: jortizdemuruaferrero@gmail.com
Maintainer: Joaquin Ortiz de Murua Ferrero
Maintainer-email: jortizdemuruaferrero@gmail.com
License: MIT license
Keywords: instance semantic segmentation pytorch tensorflow huggingface opencv embedding image analysis machine learning deep learning active learning computer vision
Classifier: Development Status :: 4 - Beta
Classifier: Programming Language :: Python :: 3.10
Classifier: Intended Audience :: Science/Research
Classifier: Intended Audience :: Developers
Classifier: Topic :: Scientific/Engineering :: Image Recognition
Classifier: Topic :: Scientific/Engineering :: Artificial Intelligence
Classifier: Operating System :: OS Independent
License-File: LICENSE.txt
Requires-Dist: kneed==0.8.5
Requires-Dist: lpips==0.1.4
Requires-Dist: matplotlib<4.0.0,>=3.7.0
Requires-Dist: numpy<2.0.0,>=1.25.0
Requires-Dist: opencv_contrib_python<5.0.0,>=4.8.0
Requires-Dist: opencv_python<5.0.0,>=4.8.0
Requires-Dist: opencv_python_headless<5.0.0,>=4.8.0
Requires-Dist: pandas==2.2.3
Requires-Dist: Pillow<12.0.0,>=10.0.0
Requires-Dist: piq==0.8.0
Requires-Dist: scikit-learn<1.5.0,>=1.3.0
Requires-Dist: scipy<2.0.0,>=1.11.0
Requires-Dist: scikit-image<1.0.0,>=0.21.0
Requires-Dist: tensorflow<3.0.0,>=2.13.0
Requires-Dist: tqdm<5.0.0,>=4.65.0
Requires-Dist: transformers<5.0.0,>=4.33.0
Requires-Dist: medimageinsights>=0.1.0
Dynamic: author
Dynamic: author-email
Dynamic: classifier
Dynamic: description
Dynamic: description-content-type
Dynamic: home-page
Dynamic: keywords
Dynamic: license
Dynamic: license-file
Dynamic: maintainer
Dynamic: maintainer-email
Dynamic: requires-dist
Dynamic: summary
